soit
