Metadata-Version: 2.1
Name: soit
Version: 0.2.3
Summary: a simple tool for verifying if a container image is compatible with Apache Spark operator for Kubernetes and OpenShift
Home-page: https://github.com/Jiri-Kremser/spark-operator-image-tool
Maintainer: Jiri Kremser
Maintainer-email: foo@bar.com
License: Apache-2
Platform: UNKNOWN
Classifier: Development Status :: 3 - Alpha
Classifier: Environment :: Console
Classifier: Intended Audience :: Developers
Classifier: License :: OSI Approved :: Apache Software License
Classifier: Operating System :: OS Independent
Classifier: Programming Language :: Python
Classifier: Programming Language :: Python :: 3
Requires-Python: >=3
